compars/__init__.py
compars/assertions/__init__.py
compars/assertions/dataframe.py
compars/dataframe/__init__.py
compars/dataframe/types.py
tests/__init__.py
tests/test_frame.py
venv/bin/activate_this.py
venv/bin/find_spark_home.py
compars-0.0.0.dist-info/LICENSE
compars-0.0.0.dist-info/METADATA
compars-0.0.0.dist-info/WHEEL
compars-0.0.0.dist-info/top_level.txt
compars-0.0.0.dist-info/RECORD
