Metadata-Version: 2.1
Name: compars
Version: 0.0.0
Summary: DataFrame comparison done right (AKA the Bear-agnostic DataFrame comparison library)
Author-email: Hadar Sharon <hadar.sharon94@gmail.com>
License: MIT License
Project-URL: Documentation, https://github.com/hadarsharon/compars/wiki
Project-URL: Repository, https://github.com/hadarsharon/compars
Project-URL: Changelog, https://github.com/hadarsharon/compars/releases
Keywords: python,rust,spark,pandas,pyspark,data-engineering,dataframe,dataframes,data-quality,data-profiling,koalas,polars
Classifier: Development Status :: 1 - Planning
Classifier: Intended Audience :: Developers
Classifier: License :: OSI Approved :: MIT License
Classifier: Operating System :: OS Independent
Classifier: Programming Language :: Python :: 3 :: Only
Classifier: Programming Language :: Python :: 3.10
Classifier: Programming Language :: Python :: 3.11
Classifier: Programming Language :: Python :: 3.12
Classifier: Programming Language :: Rust
Classifier: Topic :: Scientific/Engineering
Classifier: Topic :: Software Development
Classifier: Topic :: Software Development :: Libraries
Classifier: Topic :: Software Development :: Quality Assurance
Classifier: Topic :: Software Development :: Testing
Requires-Python: >=3.10
License-File: LICENSE
